odoo/addons/purchase_report_viewer/__init__.py
odoo/addons/purchase_report_viewer/__manifest__.py
odoo/addons/purchase_report_viewer/static/description/icon.png
odoo/addons/purchase_report_viewer/views/purchase.xml
odoo12_addon_purchase_report_viewer-12.0.1.0.0.99.dev3.dist-info/METADATA
odoo12_addon_purchase_report_viewer-12.0.1.0.0.99.dev3.dist-info/WHEEL
odoo12_addon_purchase_report_viewer-12.0.1.0.0.99.dev3.dist-info/top_level.txt
odoo12_addon_purchase_report_viewer-12.0.1.0.0.99.dev3.dist-info/RECORD
